snakemake_object/__init__.py
snakemake_object/bash.py
snakemake_object/julia.py
snakemake_object/python.py
snakemake_object/r.py
snakemake_object-1.0.0.dist-info/LICENSE
snakemake_object-1.0.0.dist-info/METADATA
snakemake_object-1.0.0.dist-info/WHEEL
snakemake_object-1.0.0.dist-info/RECORD
